{
  "Sakata": [
    [
      0,
      [
        0.0,
        0.0,
        0.33,
        0.33
      ]
    ]
  ],
  "Zhao Yangren": [
    [
      0,
      [
        0.33,
        0.0,
        0.67,
        0.33
      ]
    ]
  ],
  "Hu Shuisheng": [
    [
      0,
      [
        0.67,
        0.0,
        1.0,
        0.33
      ]
    ]
  ],
  "Yu Mancang": [
    [
      0,
      [
        0.0,
        0.33,
        0.33,
        0.67
      ]
    ]
  ],
  "Showlian": [
    [
      0,
      [
        0.33,
        0.33,
        0.67,
        0.67
      ]
    ]
  ],
  "Bingkun Uncle": [
    [
      0,
      [
        0.67,
        0.33,
        1.0,
        0.67
      ]
    ]
  ],
  "He Hua": [
    [
      0,
      [
        0.0,
        0.67,
        0.33,
        1.0
      ]
    ]
  ]
}