{
  "Chen Xiang": [
    [
      0,
      [
        0.0,
        0.0,
        0.33,
        0.33
      ]
    ]
  ],
  "Yin Xiang": [
    [
      0,
      [
        0.33,
        0.0,
        0.67,
        0.33
      ]
    ]
  ],
  "Chun Shou": [
    [
      0,
      [
        0.67,
        0.0,
        1.0,
        0.33
      ]
    ]
  ],
  "Sh\u00ec W\u00e8i": [
    [
      0,
      [
        0.0,
        0.33,
        0.33,
        0.67
      ]
    ]
  ],
  "Imperial Physician": [
    [
      0,
      [
        0.33,
        0.33,
        0.67,
        0.67
      ]
    ]
  ]
}